multidocker/__init__.py
multidocker/app.py
multidocker/command.py
multidocker/composefile.py
multidocker/multidocker.py
multidocker/test.py
multidocker/util.py
multidocker/volume.py
multidocker-1.0.4.dist-info/LICENSE.txt
multidocker-1.0.4.dist-info/METADATA
multidocker-1.0.4.dist-info/RECORD
multidocker-1.0.4.dist-info/WHEEL
multidocker-1.0.4.dist-info/entry_points.txt
multidocker-1.0.4.dist-info/top_level.txt
