Metadata-Version: 2.1
Name: multidocker
Version: 1.0.4
Summary: Run multiple docker-compose files together
Home-page: https://github.com/techhazard/multidocker
Author: techhazard
Author-email: techhazard@codeforyouand.me
License: UNKNOWN
Project-URL: Bug Reports, https://github.com/techhazard/multidocker/issues
Project-URL: Funding, https://donate.pypi.org
Project-URL: Source, https://github.com/techhazard/multidocker
Keywords: docker docker-compose repl
Platform: UNKNOWN
Classifier: Development Status :: 4 - Beta
Classifier: License :: OSI Approved :: GNU General Public License v3 or later (GPLv3+)
Classifier: Programming Language :: Python :: 3.6
Provides-Extra: dev
Provides-Extra: test
Requires-Dist: ruamel.yaml
Provides-Extra: dev
Requires-Dist: check-manifest; extra == 'dev'
Provides-Extra: test
Requires-Dist: coverage; extra == 'test'
